{"info":{"file":"app/javascripts/controllers/mapController.js","fileShort":"app/javascripts/controllers/mapController.js","fileSafe":"app_javascripts_controllers_mapController_js","link":"files/app_javascripts_controllers_mapController_js/index.html"},"complexity":{"aggregate":{"line":1,"complexity":{"sloc":{"physical":583,"logical":395},"cyclomatic":81,"halstead":{"operators":{"distinct":37,"total":1302,"identifiers":["__stripped__"]},"operands":{"distinct":347,"total":1614,"identifiers":["__stripped__"]},"length":2916,"vocabulary":384,"difficulty":86.04899135446686,"volume":25033.75065210289,"effort":2154128.993432681,"bugs":8.344583550700964,"time":119673.83296848228},"params":84}},"functions":[{"name":"<anonymous>","line":1,"complexity":{"sloc":{"physical":583,"logical":50},"cyclomatic":6,"halstead":{"operators":{"distinct":11,"total":132,"identifiers":["__stripped__"]},"operands":{"distinct":77,"total":177,"identifiers":["__stripped__"]},"length":309,"vocabulary":88,"difficulty":12.642857142857142,"volume":1995.9643701589252,"effort":25234.692394152124,"bugs":0.6653214567196417,"time":1401.9273552306736},"params":10}},{"name":"<anonymous>","line":18,"complexity":{"sloc":{"physical":3,"logical":1},"cyclomatic":1,"halstead":{"operators":{"distinct":3,"total":5,"identifiers":["__stripped__"]},"operands":{"distinct":3,"total":5,"identifiers":["__stripped__"]},"length":10,"vocabulary":6,"difficulty":2.5,"volume":25.84962500721156,"effort":64.62406251802891,"bugs":0.00861654166907052,"time":3.5902256954460503},"params":0}},{"name":"<anonymous>","line":28,"complexity":{"sloc":{"physical":10,"logical":3},"cyclomatic":3,"halstead":{"operators":{"distinct":8,"total":30,"identifiers":["__stripped__"]},"operands":{"distinct":13,"total":35,"identifiers":["__stripped__"]},"length":65,"vocabulary":21,"difficulty":10.76923076923077,"volume":285.50063248061946,"effort":3074.6221959451327,"bugs":0.09516687749353982,"time":170.81234421917404},"params":1}},{"name":"noConsultableAssets","line":39,"complexity":{"sloc":{"physical":24,"logical":9},"cyclomatic":3,"halstead":{"operators":{"distinct":10,"total":32,"identifiers":["__stripped__"]},"operands":{"distinct":28,"total":36,"identifiers":["__stripped__"]},"length":68,"vocabulary":38,"difficulty":6.428571428571429,"volume":356.8590709141638,"effort":2294.094027305339,"bugs":0.1189530236380546,"time":127.44966818362994},"params":1}},{"name":"<anonymous>","line":43,"complexity":{"sloc":{"physical":6,"logical":3},"cyclomatic":2,"halstead":{"operators":{"distinct":5,"total":20,"identifiers":["__stripped__"]},"operands":{"distinct":15,"total":20,"identifiers":["__stripped__"]},"length":40,"vocabulary":20,"difficulty":3.333333333333333,"volume":172.8771237954945,"effort":576.2570793183149,"bugs":0.0576257079318315,"time":32.01428218435083},"params":0}},{"name":"<anonymous>","line":55,"complexity":{"sloc":{"physical":3,"logical":1},"cyclomatic":1,"halstead":{"operators":{"distinct":2,"total":4,"identifiers":["__stripped__"]},"operands":{"distinct":4,"total":4,"identifiers":["__stripped__"]},"length":8,"vocabulary":6,"difficulty":1,"volume":20.67970000576925,"effort":20.67970000576925,"bugs":0.006893233335256416,"time":1.1488722225427361},"params":0}},{"name":"<anonymous>","line":65,"complexity":{"sloc":{"physical":121,"logical":49},"cyclomatic":7,"halstead":{"operators":{"distinct":20,"total":122,"identifiers":["__stripped__"]},"operands":{"distinct":84,"total":155,"identifiers":["__stripped__"]},"length":277,"vocabulary":104,"difficulty":18.452380952380953,"volume":1856.0218019250824,"effort":34248.02134504617,"bugs":0.6186739339750275,"time":1902.6678525025648},"params":1}},{"name":"<anonymous>","line":126,"complexity":{"sloc":{"physical":3,"logical":1},"cyclomatic":1,"halstead":{"operators":{"distinct":2,"total":3,"identifiers":["__stripped__"]},"operands":{"distinct":4,"total":4,"identifiers":["__stripped__"]},"length":7,"vocabulary":6,"difficulty":1,"volume":18.094737505048094,"effort":18.094737505048094,"bugs":0.006031579168349364,"time":1.0052631947248942},"params":0}},{"name":"<anonymous>","line":134,"complexity":{"sloc":{"physical":50,"logical":1},"cyclomatic":1,"halstead":{"operators":{"distinct":4,"total":5,"identifiers":["__stripped__"]},"operands":{"distinct":11,"total":14,"identifiers":["__stripped__"]},"length":19,"vocabulary":15,"difficulty":2.5454545454545454,"volume":74.23092131656186,"effort":188.9514360785211,"bugs":0.024743640438853954,"time":10.497302004362284},"params":1}},{"name":"<anonymous>","line":136,"complexity":{"sloc":{"physical":47,"logical":33},"cyclomatic":8,"halstead":{"operators":{"distinct":17,"total":96,"identifiers":["__stripped__"]},"operands":{"distinct":43,"total":115,"identifiers":["__stripped__"]},"length":211,"vocabulary":60,"difficulty":22.732558139534884,"volume":1246.3539156733975,"effort":28332.812850482467,"bugs":0.41545130522446583,"time":1574.045158360137},"params":2}},{"name":"<anonymous>","line":188,"complexity":{"sloc":{"physical":7,"logical":4},"cyclomatic":2,"halstead":{"operators":{"distinct":6,"total":22,"identifiers":["__stripped__"]},"operands":{"distinct":13,"total":28,"identifiers":["__stripped__"]},"length":50,"vocabulary":19,"difficulty":6.461538461538462,"volume":212.39637567217926,"effort":1372.4073504971584,"bugs":0.07079879189072642,"time":76.24485280539768},"params":2}},{"name":"<anonymous>","line":196,"complexity":{"sloc":{"physical":8,"logical":6},"cyclomatic":2,"halstead":{"operators":{"distinct":9,"total":26,"identifiers":["__stripped__"]},"operands":{"distinct":19,"total":34,"identifiers":["__stripped__"]},"length":60,"vocabulary":28,"difficulty":8.052631578947368,"volume":288.44129532345625,"effort":2322.7114833941478,"bugs":0.09614709844115209,"time":129.03952685523043},"params":3}},{"name":"<anonymous>","line":205,"complexity":{"sloc":{"physical":6,"logical":3},"cyclomatic":2,"halstead":{"operators":{"distinct":4,"total":8,"identifiers":["__stripped__"]},"operands":{"distinct":5,"total":9,"identifiers":["__stripped__"]},"length":17,"vocabulary":9,"difficulty":3.6,"volume":53.88872502451932,"effort":193.99941008826954,"bugs":0.017962908341506437,"time":10.777745004903863},"params":0}},{"name":"<anonymous>","line":214,"complexity":{"sloc":{"physical":3,"logical":1},"cyclomatic":1,"halstead":{"operators":{"distinct":1,"total":1,"identifiers":["__stripped__"]},"operands":{"distinct":2,"total":2,"identifiers":["__stripped__"]},"length":3,"vocabulary":3,"difficulty":0.5,"volume":4.754887502163469,"effort":2.3774437510817346,"bugs":0.0015849625007211565,"time":0.1320802083934297},"params":1}},{"name":"<anonymous>","line":222,"complexity":{"sloc":{"physical":3,"logical":1},"cyclomatic":1,"halstead":{"operators":{"distinct":2,"total":2,"identifiers":["__stripped__"]},"operands":{"distinct":4,"total":5,"identifiers":["__stripped__"]},"length":7,"vocabulary":6,"difficulty":1.25,"volume":18.094737505048094,"effort":22.61842188131012,"bugs":0.006031579168349364,"time":1.2565789934061178},"params":2}},{"name":"<anonymous>","line":225,"complexity":{"sloc":{"physical":3,"logical":1},"cyclomatic":1,"halstead":{"operators":{"distinct":2,"total":2,"identifiers":["__stripped__"]},"operands":{"distinct":4,"total":5,"identifiers":["__stripped__"]},"length":7,"vocabulary":6,"difficulty":1.25,"volume":18.094737505048094,"effort":22.61842188131012,"bugs":0.006031579168349364,"time":1.2565789934061178},"params":2}},{"name":"<anonymous>","line":228,"complexity":{"sloc":{"physical":3,"logical":1},"cyclomatic":1,"halstead":{"operators":{"distinct":2,"total":2,"identifiers":["__stripped__"]},"operands":{"distinct":4,"total":5,"identifiers":["__stripped__"]},"length":7,"vocabulary":6,"difficulty":1.25,"volume":18.094737505048094,"effort":22.61842188131012,"bugs":0.006031579168349364,"time":1.2565789934061178},"params":2}},{"name":"<anonymous>","line":232,"complexity":{"sloc":{"physical":5,"logical":3},"cyclomatic":2,"halstead":{"operators":{"distinct":7,"total":9,"identifiers":["__stripped__"]},"operands":{"distinct":9,"total":16,"identifiers":["__stripped__"]},"length":25,"vocabulary":16,"difficulty":6.222222222222221,"volume":100,"effort":622.2222222222222,"bugs":0.03333333333333333,"time":34.5679012345679},"params":4}},{"name":"<anonymous>","line":237,"complexity":{"sloc":{"physical":5,"logical":3},"cyclomatic":2,"halstead":{"operators":{"distinct":7,"total":9,"identifiers":["__stripped__"]},"operands":{"distinct":7,"total":12,"identifiers":["__stripped__"]},"length":21,"vocabulary":14,"difficulty":6,"volume":79.95445336320968,"effort":479.7267201792581,"bugs":0.026651484454403226,"time":26.651484454403228},"params":2}},{"name":"<anonymous>","line":242,"complexity":{"sloc":{"physical":3,"logical":1},"cyclomatic":1,"halstead":{"operators":{"distinct":2,"total":2,"identifiers":["__stripped__"]},"operands":{"distinct":3,"total":3,"identifiers":["__stripped__"]},"length":5,"vocabulary":5,"difficulty":1,"volume":11.60964047443681,"effort":11.60964047443681,"bugs":0.0038698801581456034,"time":0.6449800263576005},"params":1}},{"name":"<anonymous>","line":249,"complexity":{"sloc":{"physical":5,"logical":2},"cyclomatic":2,"halstead":{"operators":{"distinct":3,"total":10,"identifiers":["__stripped__"]},"operands":{"distinct":10,"total":15,"identifiers":["__stripped__"]},"length":25,"vocabulary":13,"difficulty":2.25,"volume":92.5109929535273,"effort":208.14973414543644,"bugs":0.030836997651175767,"time":11.563874119190913},"params":4}},{"name":"<anonymous>","line":255,"complexity":{"sloc":{"physical":26,"logical":16},"cyclomatic":7,"halstead":{"operators":{"distinct":19,"total":88,"identifiers":["__stripped__"]},"operands":{"distinct":40,"total":100,"identifiers":["__stripped__"]},"length":188,"vocabulary":59,"difficulty":23.75,"volume":1105.9368932800262,"effort":26266.00121540062,"bugs":0.3686456310933421,"time":1459.222289744479},"params":5}},{"name":"iconCreateFunction","line":258,"complexity":{"sloc":{"physical":3,"logical":4},"cyclomatic":1,"halstead":{"operators":{"distinct":7,"total":13,"identifiers":["__stripped__"]},"operands":{"distinct":13,"total":16,"identifiers":["__stripped__"]},"length":29,"vocabulary":20,"difficulty":4.307692307692308,"volume":125.33591475173351,"effort":539.9085558536214,"bugs":0.041778638250577836,"time":29.99491976964563},"params":1}},{"name":"<anonymous>","line":272,"complexity":{"sloc":{"physical":5,"logical":1},"cyclomatic":1,"halstead":{"operators":{"distinct":3,"total":3,"identifiers":["__stripped__"]},"operands":{"distinct":5,"total":6,"identifiers":["__stripped__"]},"length":9,"vocabulary":8,"difficulty":1.7999999999999998,"volume":27,"effort":48.599999999999994,"bugs":0.009,"time":2.6999999999999997},"params":2}},{"name":"<anonymous>","line":273,"complexity":{"sloc":{"physical":3,"logical":1},"cyclomatic":1,"halstead":{"operators":{"distinct":2,"total":2,"identifiers":["__stripped__"]},"operands":{"distinct":4,"total":4,"identifiers":["__stripped__"]},"length":6,"vocabulary":6,"difficulty":1,"volume":15.509775004326936,"effort":15.509775004326936,"bugs":0.005169925001442312,"time":0.861654166907052},"params":0}},{"name":"<anonymous>","line":282,"complexity":{"sloc":{"physical":5,"logical":2},"cyclomatic":2,"halstead":{"operators":{"distinct":4,"total":12,"identifiers":["__stripped__"]},"operands":{"distinct":11,"total":17,"identifiers":["__stripped__"]},"length":29,"vocabulary":15,"difficulty":3.090909090909091,"volume":113.29982727264704,"effort":350.19946611545447,"bugs":0.03776660909088234,"time":19.455525895303026},"params":4}},{"name":"<anonymous>","line":289,"complexity":{"sloc":{"physical":10,"logical":6},"cyclomatic":4,"halstead":{"operators":{"distinct":11,"total":31,"identifiers":["__stripped__"]},"operands":{"distinct":15,"total":33,"identifiers":["__stripped__"]},"length":64,"vocabulary":26,"difficulty":12.100000000000001,"volume":300.8281419610299,"effort":3640.0205177284624,"bugs":0.10027604732034331,"time":202.22336209602568},"params":2}},{"name":"<anonymous>","line":301,"complexity":{"sloc":{"physical":16,"logical":11},"cyclomatic":6,"halstead":{"operators":{"distinct":18,"total":81,"identifiers":["__stripped__"]},"operands":{"distinct":39,"total":93,"identifiers":["__stripped__"]},"length":174,"vocabulary":57,"difficulty":21.46153846153846,"volume":1014.9228624646652,"effort":21781.80604828012,"bugs":0.3383076208215551,"time":1210.100336015562},"params":5}},{"name":"iconCreateFunction","line":303,"complexity":{"sloc":{"physical":3,"logical":4},"cyclomatic":1,"halstead":{"operators":{"distinct":7,"total":13,"identifiers":["__stripped__"]},"operands":{"distinct":13,"total":16,"identifiers":["__stripped__"]},"length":29,"vocabulary":20,"difficulty":4.307692307692308,"volume":125.33591475173351,"effort":539.9085558536214,"bugs":0.041778638250577836,"time":29.99491976964563},"params":1}},{"name":"<anonymous>","line":318,"complexity":{"sloc":{"physical":3,"logical":1},"cyclomatic":2,"halstead":{"operators":{"distinct":3,"total":9,"identifiers":["__stripped__"]},"operands":{"distinct":9,"total":13,"identifiers":["__stripped__"]},"length":22,"vocabulary":12,"difficulty":2.1666666666666665,"volume":78.86917501586544,"effort":170.8832125343751,"bugs":0.026289725005288478,"time":9.493511807465284},"params":2}},{"name":"<anonymous>","line":321,"complexity":{"sloc":{"physical":8,"logical":5},"cyclomatic":2,"halstead":{"operators":{"distinct":5,"total":22,"identifiers":["__stripped__"]},"operands":{"distinct":9,"total":26,"identifiers":["__stripped__"]},"length":48,"vocabulary":14,"difficulty":7.222222222222222,"volume":182.75303625876498,"effort":1319.883039646636,"bugs":0.06091767875292166,"time":73.32683553592422},"params":2}},{"name":"<anonymous>","line":329,"complexity":{"sloc":{"physical":33,"logical":21},"cyclomatic":8,"halstead":{"operators":{"distinct":14,"total":88,"identifiers":["__stripped__"]},"operands":{"distinct":34,"total":98,"identifiers":["__stripped__"]},"length":186,"vocabulary":48,"difficulty":20.176470588235293,"volume":1038.8030251341352,"effort":20959.378683588726,"bugs":0.34626767504471173,"time":1164.4099268660402},"params":3}},{"name":"style","line":344,"complexity":{"sloc":{"physical":3,"logical":4},"cyclomatic":1,"halstead":{"operators":{"distinct":4,"total":7,"identifiers":["__stripped__"]},"operands":{"distinct":8,"total":10,"identifiers":["__stripped__"]},"length":17,"vocabulary":12,"difficulty":2.5,"volume":60.94436251225966,"effort":152.36090628064915,"bugs":0.020314787504086555,"time":8.464494793369397},"params":1}},{"name":"makeControl","line":365,"complexity":{"sloc":{"physical":13,"logical":5},"cyclomatic":1,"halstead":{"operators":{"distinct":9,"total":13,"identifiers":["__stripped__"]},"operands":{"distinct":12,"total":15,"identifiers":["__stripped__"]},"length":28,"vocabulary":21,"difficulty":5.625,"volume":122.9848878378053,"effort":691.7899940876548,"bugs":0.04099496261260177,"time":38.43277744931416},"params":3}},{"name":"onAdd","line":368,"complexity":{"sloc":{"physical":7,"logical":3},"cyclomatic":1,"halstead":{"operators":{"distinct":6,"total":15,"identifiers":["__stripped__"]},"operands":{"distinct":17,"total":19,"identifiers":["__stripped__"]},"length":34,"vocabulary":23,"difficulty":3.3529411764705883,"volume":153.80110650593844,"effort":515.6860629904995,"bugs":0.05126703550197948,"time":28.649225721694418},"params":1}},{"name":"activatePosition","line":384,"complexity":{"sloc":{"physical":40,"logical":18},"cyclomatic":4,"halstead":{"operators":{"distinct":10,"total":40,"identifiers":["__stripped__"]},"operands":{"distinct":29,"total":50,"identifiers":["__stripped__"]},"length":90,"vocabulary":39,"difficulty":8.620689655172413,"volume":475.6861996976024,"effort":4100.7431008414,"bugs":0.15856206656586747,"time":227.81906115785554},"params":1}},{"name":"ChromiumCallbacks.undefined","line":398,"complexity":{"sloc":{"physical":4,"logical":2},"cyclomatic":1,"halstead":{"operators":{"distinct":2,"total":2,"identifiers":["__stripped__"]},"operands":{"distinct":7,"total":9,"identifiers":["__stripped__"]},"length":11,"vocabulary":9,"difficulty":1.2857142857142858,"volume":34.86917501586544,"effort":44.831796448969854,"bugs":0.011623058338621813,"time":2.490655358276103},"params":3}},{"name":"<anonymous>","line":405,"complexity":{"sloc":{"physical":7,"logical":4},"cyclomatic":2,"halstead":{"operators":{"distinct":5,"total":10,"identifiers":["__stripped__"]},"operands":{"distinct":11,"total":11,"identifiers":["__stripped__"]},"length":21,"vocabulary":16,"difficulty":2.5,"volume":84,"effort":210,"bugs":0.028,"time":11.666666666666666},"params":0}},{"name":"<anonymous>","line":416,"complexity":{"sloc":{"physical":4,"logical":2},"cyclomatic":1,"halstead":{"operators":{"distinct":2,"total":5,"identifiers":["__stripped__"]},"operands":{"distinct":6,"total":6,"identifiers":["__stripped__"]},"length":11,"vocabulary":8,"difficulty":1,"volume":33,"effort":33,"bugs":0.011,"time":1.8333333333333333},"params":0}},{"name":"stopPosition","line":425,"complexity":{"sloc":{"physical":8,"logical":5},"cyclomatic":2,"halstead":{"operators":{"distinct":5,"total":11,"identifiers":["__stripped__"]},"operands":{"distinct":8,"total":12,"identifiers":["__stripped__"]},"length":23,"vocabulary":13,"difficulty":3.75,"volume":85.11011351724513,"effort":319.16292568966924,"bugs":0.028370037839081708,"time":17.73127364942607},"params":0}},{"name":"removePositionMarker","line":434,"complexity":{"sloc":{"physical":8,"logical":4},"cyclomatic":3,"halstead":{"operators":{"distinct":4,"total":12,"identifiers":["__stripped__"]},"operands":{"distinct":6,"total":14,"identifiers":["__stripped__"]},"length":26,"vocabulary":10,"difficulty":4.666666666666667,"volume":86.37013046707143,"effort":403.06060884633337,"bugs":0.028790043489023812,"time":22.39225604701852},"params":0}},{"name":"setLocationMarker","line":443,"complexity":{"sloc":{"physical":40,"logical":27},"cyclomatic":3,"halstead":{"operators":{"distinct":12,"total":68,"identifiers":["__stripped__"]},"operands":{"distinct":49,"total":91,"identifiers":["__stripped__"]},"length":159,"vocabulary":61,"difficulty":11.142857142857142,"volume":942.987236672499,"effort":10507.572065779274,"bugs":0.314329078890833,"time":583.7540036544041},"params":3}},{"name":"<anonymous>","line":468,"complexity":{"sloc":{"physical":3,"logical":1},"cyclomatic":1,"halstead":{"operators":{"distinct":2,"total":3,"identifiers":["__stripped__"]},"operands":{"distinct":4,"total":4,"identifiers":["__stripped__"]},"length":7,"vocabulary":6,"difficulty":1,"volume":18.094737505048094,"effort":18.094737505048094,"bugs":0.006031579168349364,"time":1.0052631947248942},"params":0}},{"name":"<anonymous>","line":478,"complexity":{"sloc":{"physical":3,"logical":1},"cyclomatic":1,"halstead":{"operators":{"distinct":2,"total":3,"identifiers":["__stripped__"]},"operands":{"distinct":4,"total":4,"identifiers":["__stripped__"]},"length":7,"vocabulary":6,"difficulty":1,"volume":18.094737505048094,"effort":18.094737505048094,"bugs":0.006031579168349364,"time":1.0052631947248942},"params":0}},{"name":"activateConsultation","line":489,"complexity":{"sloc":{"physical":12,"logical":7},"cyclomatic":3,"halstead":{"operators":{"distinct":5,"total":15,"identifiers":["__stripped__"]},"operands":{"distinct":15,"total":20,"identifiers":["__stripped__"]},"length":35,"vocabulary":20,"difficulty":3.333333333333333,"volume":151.26748332105768,"effort":504.22494440352557,"bugs":0.05042249444035256,"time":28.012496911306975},"params":1}},{"name":"stopConsultation","line":502,"complexity":{"sloc":{"physical":7,"logical":4},"cyclomatic":2,"halstead":{"operators":{"distinct":6,"total":9,"identifiers":["__stripped__"]},"operands":{"distinct":8,"total":11,"identifiers":["__stripped__"]},"length":20,"vocabulary":14,"difficulty":4.125,"volume":76.14709844115208,"effort":314.10678106975234,"bugs":0.025382366147050694,"time":17.450376726097353},"params":0}},{"name":"$scope.highlightAsset","line":512,"complexity":{"sloc":{"physical":32,"logical":29},"cyclomatic":9,"halstead":{"operators":{"distinct":14,"total":94,"identifiers":["__stripped__"]},"operands":{"distinct":41,"total":111,"identifiers":["__stripped__"]},"length":205,"vocabulary":55,"difficulty":18.951219512195124,"volume":1185.1787412725553,"effort":22460.582487043306,"bugs":0.3950595804241851,"time":1247.8101381690726},"params":3}},{"name":"<anonymous>","line":513,"complexity":{"sloc":{"physical":1,"logical":1},"cyclomatic":1,"halstead":{"operators":{"distinct":2,"total":2,"identifiers":["__stripped__"]},"operands":{"distinct":3,"total":3,"identifiers":["__stripped__"]},"length":5,"vocabulary":5,"difficulty":1,"volume":11.60964047443681,"effort":11.60964047443681,"bugs":0.0038698801581456034,"time":0.6449800263576005},"params":0}},{"name":"<anonymous>","line":538,"complexity":{"sloc":{"physical":3,"logical":1},"cyclomatic":1,"halstead":{"operators":{"distinct":2,"total":2,"identifiers":["__stripped__"]},"operands":{"distinct":3,"total":3,"identifiers":["__stripped__"]},"length":5,"vocabulary":5,"difficulty":1,"volume":11.60964047443681,"effort":11.60964047443681,"bugs":0.0038698801581456034,"time":0.6449800263576005},"params":0}},{"name":"$scope.unHighlightAsset","line":545,"complexity":{"sloc":{"physical":6,"logical":3},"cyclomatic":2,"halstead":{"operators":{"distinct":3,"total":12,"identifiers":["__stripped__"]},"operands":{"distinct":7,"total":14,"identifiers":["__stripped__"]},"length":26,"vocabulary":10,"difficulty":3,"volume":86.37013046707143,"effort":259.1103914012143,"bugs":0.028790043489023812,"time":14.395021744511906},"params":1}},{"name":"$scope.unHighlightAllAsset","line":552,"complexity":{"sloc":{"physical":8,"logical":5},"cyclomatic":3,"halstead":{"operators":{"distinct":8,"total":17,"identifiers":["__stripped__"]},"operands":{"distinct":8,"total":18,"identifiers":["__stripped__"]},"length":35,"vocabulary":16,"difficulty":9,"volume":140,"effort":1260,"bugs":0.04666666666666667,"time":70},"params":0}},{"name":"$scope.zoomOnAsset","line":561,"complexity":{"sloc":{"physical":21,"logical":19},"cyclomatic":5,"halstead":{"operators":{"distinct":9,"total":53,"identifiers":["__stripped__"]},"operands":{"distinct":23,"total":62,"identifiers":["__stripped__"]},"length":115,"vocabulary":32,"difficulty":12.130434782608695,"volume":575,"effort":6975,"bugs":0.19166666666666668,"time":387.5},"params":1}}],"maintainability":63.95515665620639,"params":1.6153846153846154,"module":"app/javascripts/controllers/mapController.js"},"jshint":{"messages":[{"severity":"error","line":19,"column":59,"message":"Expected an assignment or function call and instead saw an expression.","source":"Expected an assignment or function call and instead saw an expression."},{"severity":"error","line":120,"column":29,"message":"Bad line breaking before '?'.","source":"Bad line breaking before '{a}'."},{"severity":"error","line":276,"column":14,"message":"Don't make functions within a loop.","source":"Don't make functions within a loop."}]}}